<?xml version="1.0" encoding="UTF-8"?>
<tv generator-info-name="WebGrab+Plus/w MDB &amp; REX Postprocess -- version  V2.1 -- Jan van Straaten" generator-info-url="http://www.webgrabplus.com">
  <channel id="1000 X HORA">
    <display-name lang="es">1000 X HORA</display-name>
    <url>http://www.http://tv.vera.com.uy</url>
  </channel>
  <channel id="VTV">
    <display-name lang="es">VTV</display-name>
    <url>http://www.http://tv.vera.com.uy</url>
  </channel>
  <channel id="Televisión Nacional">
    <display-name lang="es">Televisión Nacional</display-name>
    <url>http://www.http://tv.vera.com.uy</url>
  </channel>
  <channel id="Monte Carlo TV">
    <display-name lang="es">Monte Carlo TV</display-name>
    <url>http://www.http://tv.vera.com.uy</url>
  </channel>
  <channel id="Canal 12 Melo">
    <display-name lang="es">Canal 12 Melo</display-name>
    <url>http://www.http://tv.vera.com.uy</url>
  </channel>
  <channel id="RTV">
    <display-name lang="es">RTV</display-name>
    <url>http://www.http://tv.vera.com.uy</url>
  </channel>
  <channel id="Tevé Ciudad">
    <display-name lang="es">Tevé Ciudad</display-name>
    <url>http://www.http://tv.vera.com.uy</url>
  </channel>
  <channel id="A + V">
    <display-name lang="es">A + V</display-name>
    <url>http://www.http://tv.vera.com.uy</url>
  </channel>
  <channel id="Vera+ HD">
    <display-name lang="es">Vera+ HD</display-name>
    <url>http://www.http://tv.vera.com.uy</url>
  </channel>
  <channel id="Canal 7 Punta">
    <display-name lang="es">Canal 7 Punta</display-name>
    <url>http://www.http://tv.vera.com.uy</url>
  </channel>
  <channel id="Artigas Televisión">
    <display-name lang="es">Artigas Televisión</display-name>
    <url>http://www.http://tv.vera.com.uy</url>
  </channel>
  <channel id="Canal 2 Lascano">
    <display-name lang="es">Canal 2 Lascano</display-name>
    <url>http://www.http://tv.vera.com.uy</url>
  </channel>
  <channel id="Soy Tacuarembó TV">
    <display-name lang="es">Soy Tacuarembó TV</display-name>
    <url>http://www.http://tv.vera.com.uy</url>
  </channel>
  <channel id="Canal 8 de Rocha">
    <display-name lang="es">Canal 8 de Rocha</display-name>
    <url>http://www.http://tv.vera.com.uy</url>
  </channel>
  <channel id="Cámara de Representantes">
    <display-name lang="es">Cámara de Representantes</display-name>
    <url>http://www.http://tv.vera.com.uy</url>
  </channel>
  <channel id="VTV+">
    <display-name lang="es">VTV+</display-name>
    <url>http://www.http://tv.vera.com.uy</url>
  </channel>
  <channel id="Canal 11 Treinta y Tres">
    <display-name lang="es">Canal 11 Treinta y Tres</display-name>
    <url>http://www.http://tv.vera.com.uy</url>
  </channel>
  <channel id="Canal 4 Chuy">
    <display-name lang="es">Canal 4 Chuy</display-name>
    <url>http://www.http://tv.vera.com.uy</url>
  </channel>
  <channel id="1 TV Salto HD">
    <display-name lang="es">1 TV Salto HD</display-name>
    <url>http://www.http://tv.vera.com.uy</url>
  </channel>
  <channel id="Charrúa TV">
    <display-name lang="es">Charrúa TV</display-name>
    <url>http://www.http://tv.vera.com.uy</url>
  </channel>
  <channel id="Canal 4 HD Treinta y Tres">
    <display-name lang="es">Canal 4 HD Treinta y Tres</display-name>
    <url>http://www.http://tv.vera.com.uy</url>
  </channel>
  <channel id="TVL Pando">
    <display-name lang="es">TVL Pando</display-name>
    <url>http://www.http://tv.vera.com.uy</url>
  </channel>
  <channel id="Canal 4 Paysandú">
    <display-name lang="es">Canal 4 Paysandú</display-name>
    <url>http://www.http://tv.vera.com.uy</url>
  </channel>
  <channel id="Canal 4 Juan Lacaze">
    <display-name lang="es">Canal 4 Juan Lacaze</display-name>
    <url>http://www.http://tv.vera.com.uy</url>
  </channel>
  <channel id="El Canal de la Región - Noreste Canelones">
    <display-name lang="es">El Canal de la Región - Noreste Canelones</display-name>
    <url>http://www.http://tv.vera.com.uy</url>
  </channel>
  <channel id="Canal 8 Durazno">
    <display-name lang="es">Canal 8 Durazno</display-name>
    <url>http://www.http://tv.vera.com.uy</url>
  </channel>
  <channel id="Canal 4 Salto">
    <display-name lang="es">Canal 4 Salto</display-name>
    <url>http://www.http://tv.vera.com.uy</url>
  </channel>
  <channel id="Canal 2 San Carlos">
    <display-name lang="es">Canal 2 San Carlos</display-name>
    <url>http://www.http://tv.vera.com.uy</url>
  </channel>
  <channel id="DW Latinoamérica">
    <display-name lang="es">DW Latinoamérica</display-name>
    <url>http://www.http://tv.vera.com.uy</url>
  </channel>
  <channel id="Canal CV 10">
    <display-name lang="es">Canal CV 10</display-name>
    <url>http://www.http://tv.vera.com.uy</url>
  </channel>
  <programme start="20190220000000 -0300" stop="20190220000000 -0300" channel="1000 X HORA">
    <title lang="es">EVENTO CIUDAD DEL PLATA</title>
  </programme>
  <programme start="20190220000000 -0300" stop="20190220000000 -0300" channel="1000 X HORA">
    <title lang="es">ON THE ROAD</title>
  </programme>
  <programme start="20190220000000 -0300" stop="20190220000000 -0300" channel="1000 X HORA">
    <title lang="es">MUSEOS DEL MUNDO</title>
  </programme>
  <programme start="20190220000000 -0300" stop="20190220000000 -0300" channel="1000 X HORA">
    <title lang="es">ENCUENTRO SUDAMERICANO FUSCAS DURAZNO</title>
  </programme>
  <programme start="20190220000000 -0300" stop="20190220000000 -0300" channel="1000 X HORA">
    <title lang="es">1000 X HORA</title>
  </programme>
  <programme start="20190220000000 -0300" stop="20190220000000 -0300" channel="Televisión Nacional">
    <title lang="es">InfoTNU</title>
  </programme>
  <programme start="20190220000000 -0300" stop="20190220000000 -0300" channel="Televisión Nacional">
    <title lang="es">InfoTNU</title>
  </programme>
  <programme start="20190220000000 -0300" stop="20190220000000 -0300" channel="Televisión Nacional">
    <title lang="es">InfoTNU</title>
  </programme>
  <programme start="20190220000000 -0300" stop="20190220000000 -0300" channel="Televisión Nacional">
    <title lang="es">InfoTNU</title>
  </programme>
  <programme start="20190220000000 -0300" stop="20190220000000 -0300" channel="Televisión Nacional">
    <title lang="es">The A word</title>
  </programme>
  <programme start="20190220000000 -0300" stop="20190220000000 -0300" channel="Canal 12 Melo">
    <title lang="es">La Casa de las Flores</title>
  </programme>
  <programme start="20190220000000 -0300" stop="20190220000000 -0300" channel="Canal 12 Melo">
    <title lang="es">La Casa de las Flores</title>
  </programme>
  <programme start="20190220000000 -0300" stop="20190220000000 -0300" channel="Canal 12 Melo">
    <title lang="es">La Casa de las Flores</title>
  </programme>
  <programme start="20190220000000 -0300" stop="20190220000000 -0300" channel="Canal 12 Melo">
    <title lang="es">Cine</title>
  </programme>
  <programme start="20190220000000 -0300" stop="20190220000000 -0300" channel="Canal 12 Melo">
    <title lang="es">Cine</title>
  </programme>
  <programme start="20190220000000 -0300" stop="20190220000000 -0300" channel="RTV">
    <title lang="es">Respirando Fútbol</title>
  </programme>
  <programme start="20190220000000 -0300" stop="20190220000000 -0300" channel="RTV">
    <title lang="es">Respirando Fútbol</title>
  </programme>
  <programme start="20190220000000 -0300" stop="20190220000000 -0300" channel="RTV">
    <title lang="es">Respirando Fútbol</title>
  </programme>
  <programme start="20190220000000 -0300" stop="20190220000000 -0300" channel="RTV">
    <title lang="es">Videos Clip</title>
  </programme>
  <programme start="20190220000000 -0300" stop="20190220000000 -0300" channel="RTV">
    <title lang="es">Videos Clip</title>
  </programme>
  <programme start="20190220000000 -0300" stop="20190220000000 -0300" channel="A + V">
    <title lang="es">Directo al Corazón</title>
  </programme>
  <programme start="20190220000000 -0300" stop="20190220000000 -0300" channel="A + V">
    <title lang="es">Directo al Corazón</title>
  </programme>
  <programme start="20190220000000 -0300" stop="20190220000000 -0300" channel="A + V">
    <title lang="es">Directo al Corazón</title>
  </programme>
  <programme start="20190220000000 -0300" stop="20190220000000 -0300" channel="A + V">
    <title lang="es">Directo al Corazón</title>
  </programme>
  <programme start="20190220000000 -0300" stop="20190220000000 -0300" channel="A + V">
    <title lang="es">Cumbia Clip</title>
  </programme>
  <programme start="20190220000000 -0300" stop="20190220000000 -0300" channel="Vera+ HD">
    <title lang="es">Festival Jazz 2019 Capítulo 5</title>
  </programme>
  <programme start="20190220000000 -0300" stop="20190220000000 -0300" channel="Vera+ HD">
    <title lang="es">El lago de los Cisnes Capítulo 1</title>
  </programme>
  <programme start="20190220000000 -0300" stop="20190220000000 -0300" channel="Vera+ HD">
    <title lang="es">TEDx 2018 Capítulo 1</title>
  </programme>
  <programme start="20190220000000 -0300" stop="20190220000000 -0300" channel="Vera+ HD">
    <title lang="es">Marketers 2018 Capítulo 7</title>
  </programme>
  <programme start="20190220000000 -0300" stop="20190220000000 -0300" channel="Vera+ HD">
    <title lang="es">TEDx 2018 Capítulo 2</title>
  </programme>
  <programme start="20190220000000 -0300" stop="20190220000000 -0300" channel="Canal 7 Punta">
    <title lang="es">Telenoche ( Noticiero Argentino)</title>
  </programme>
  <programme start="20190220000000 -0300" stop="20190220000000 -0300" channel="Canal 7 Punta">
    <title lang="es">Telenoche (Noticiero Argentino)</title>
  </programme>
  <programme start="20190220000000 -0300" stop="20190220000000 -0300" channel="Canal 7 Punta">
    <title lang="es">Telenoche (Noticiero Argentino)</title>
  </programme>
  <programme start="20190220000000 -0300" stop="20190220000000 -0300" channel="Canal 7 Punta">
    <title lang="es">Telenoche (Noticiero Argentino)</title>
  </programme>
  <programme start="20190220000000 -0300" stop="20190220000000 -0300" channel="Canal 7 Punta">
    <title lang="es">Cine</title>
  </programme>
  <programme start="20190220000000 -0300" stop="20190220000000 -0300" channel="Artigas Televisión">
    <title lang="es">La voz</title>
  </programme>
  <programme start="20190220000000 -0300" stop="20190220000000 -0300" channel="Artigas Televisión">
    <title lang="es">Santo y seña</title>
  </programme>
  <programme start="20190220000000 -0300" stop="20190220000000 -0300" channel="Artigas Televisión">
    <title lang="es">La voz</title>
  </programme>
  <programme start="20190220000000 -0300" stop="20190220000000 -0300" channel="Artigas Televisión">
    <title lang="es">Alguien tiene que hacerlo</title>
  </programme>
  <programme start="20190220000000 -0300" stop="20190220000000 -0300" channel="Artigas Televisión">
    <title lang="es">Sábado de película: Irene, yo, y mi otro yo</title>
  </programme>
  <programme start="20190220003000 -0300" stop="20190220003000 -0300" channel="Canal 2 Lascano">
    <title lang="es">MICRO SD</title>
  </programme>
  <programme start="20190220003000 -0300" stop="20190220003000 -0300" channel="Canal 2 Lascano">
    <title lang="es">ESPACIO PUBLICITARIO</title>
  </programme>
  <programme start="20190220003000 -0300" stop="20190220003000 -0300" channel="Canal 2 Lascano">
    <title lang="es">PLAY ON</title>
  </programme>
  <programme start="20190220080000 -0300" stop="20190220080000 -0300" channel="Canal 2 Lascano">
    <title lang="es">PÁGINA 2 EL INFORMATIVO LOCAL</title>
  </programme>
  <programme start="20190221000000 -0300" stop="20190221000000 -0300" channel="Canal 2 Lascano">
    <title lang="es">LA PREVIA</title>
  </programme>
  <programme start="20190220000000 -0300" stop="20190220000000 -0300" channel="Canal 8 de Rocha">
    <title lang="es">Informativo 3ª Edición</title>
  </programme>
  <programme start="20190220000000 -0300" stop="20190220000000 -0300" channel="Canal 8 de Rocha">
    <title lang="es">Informativo 3ª Edición</title>
  </programme>
  <programme start="20190220000000 -0300" stop="20190220000000 -0300" channel="Canal 8 de Rocha">
    <title lang="es">Informativo 3ª Edición</title>
  </programme>
  <programme start="20190220000000 -0300" stop="20190220000000 -0300" channel="Canal 8 de Rocha">
    <title lang="es">Informativo 3ª Edición</title>
  </programme>
  <programme start="20190220000000 -0300" stop="20190220000000 -0300" channel="Canal 8 de Rocha">
    <title lang="es">Programacion desde Multicanal La Paloma</title>
  </programme>
  <programme start="20190220160000 -0300" stop="20190220160000 -0300" channel="Cámara de Representantes">
    <title lang="es">Sesión ordinaria de la C.RR.</title>
  </programme>
  <programme start="20190220020000 -0300" stop="20190220020000 -0300" channel="Canal 11 Treinta y Tres">
    <title lang="es">PROGRAMACION A CONFIRMAR</title>
  </programme>
  <programme start="20190220020000 -0300" stop="20190220020000 -0300" channel="Canal 11 Treinta y Tres">
    <title lang="es">PROGRAMACION A CONFIRMAR</title>
  </programme>
  <programme start="20190220020000 -0300" stop="20190220020000 -0300" channel="Canal 11 Treinta y Tres">
    <title lang="es">PROGRAMACION A CONFIRMAR</title>
  </programme>
  <programme start="20190221000000 -0300" stop="20190221000000 -0300" channel="Canal 11 Treinta y Tres">
    <title lang="es">PROGRAMACION A CONFIRMAR</title>
  </programme>
  <programme start="20190221020000 -0300" stop="20190221020000 -0300" channel="Canal 11 Treinta y Tres">
    <title lang="es">PROGRAMACION A CONFIRMAR</title>
  </programme>
  <programme start="20190220090000 -0300" stop="20190220090000 -0300" channel="Canal 4 Chuy">
    <title lang="es">Mano a Mano</title>
  </programme>
  <programme start="20190220090000 -0300" stop="20190220090000 -0300" channel="Canal 4 Chuy">
    <title lang="es">Mano a Mano</title>
  </programme>
  <programme start="20190220090000 -0300" stop="20190220090000 -0300" channel="Canal 4 Chuy">
    <title lang="es">Mano a Mano</title>
  </programme>
  <programme start="20190220190000 -0300" stop="20190220190000 -0300" channel="Canal 4 Chuy">
    <title lang="es">2 Caras</title>
  </programme>
  <programme start="20190220000000 -0300" stop="20190220000000 -0300" channel="1 TV Salto HD">
    <title lang="es">Cámara Testigo</title>
  </programme>
  <programme start="20190220010000 -0300" stop="20190220010000 -0300" channel="1 TV Salto HD">
    <title lang="es">Repetición</title>
  </programme>
  <programme start="20190220010000 -0300" stop="20190220010000 -0300" channel="1 TV Salto HD">
    <title lang="es">Repetición</title>
  </programme>
  <programme start="20190220093000 -0300" stop="20190220093000 -0300" channel="1 TV Salto HD">
    <title lang="es">CINE - Las aventuras de Tin TIn</title>
  </programme>
  <programme start="20190221000000 -0300" stop="20190221000000 -0300" channel="1 TV Salto HD">
    <title lang="es">SABADO DE PELICULA II: “LA PURGA”</title>
  </programme>
  <programme start="20190220060000 -0300" stop="20190220060000 -0300" channel="Charrúa TV">
    <title lang="es">AGRONOTICIAS CHARRÚA</title>
  </programme>
  <programme start="20190220060000 -0300" stop="20190220060000 -0300" channel="Charrúa TV">
    <title lang="es">AGRONOTICIAS CHARRÚA</title>
  </programme>
  <programme start="20190220060000 -0300" stop="20190220060000 -0300" channel="Charrúa TV">
    <title lang="es">AGRONOTICIAS CHARRÚA</title>
  </programme>
  <programme start="20190221000000 -0300" stop="20190221000000 -0300" channel="Charrúa TV">
    <title lang="es">APOSTANDO POR URUGUAY</title>
  </programme>
  <programme start="20190221000000 -0300" stop="20190221000000 -0300" channel="Charrúa TV">
    <title lang="es">CAMINOS PARA EL FOLCLORE</title>
  </programme>
  <programme start="20190220000000 -0300" stop="20190220000000 -0300" channel="Canal 4 HD Treinta y Tres">
    <title lang="es">Cable 4 Noticias (Rep)</title>
  </programme>
  <programme start="20190220000000 -0300" stop="20190220000000 -0300" channel="Canal 4 HD Treinta y Tres">
    <title lang="es">Cable 4 Noticias (Rep)</title>
  </programme>
  <programme start="20190220000000 -0300" stop="20190220000000 -0300" channel="Canal 4 HD Treinta y Tres">
    <title lang="es">Cable 4 Noticias (Rep)</title>
  </programme>
  <programme start="20190220000000 -0300" stop="20190220000000 -0300" channel="Canal 4 HD Treinta y Tres">
    <title lang="es">Cable 4 Noticias (Rep)</title>
  </programme>
  <programme start="20190220000000 -0300" stop="20190220000000 -0300" channel="Canal 4 HD Treinta y Tres">
    <title lang="es">Cine</title>
  </programme>
  <programme start="20190220063000 -0300" stop="20190220063000 -0300" channel="Canal 4 Paysandú">
    <title lang="es">Entre Mates y Guitarras</title>
  </programme>
  <programme start="20190220063000 -0300" stop="20190220063000 -0300" channel="Canal 4 Paysandú">
    <title lang="es">Canto de aquí nomás</title>
  </programme>
  <programme start="20190220073000 -0300" stop="20190220073000 -0300" channel="Canal 4 Paysandú">
    <title lang="es">Primer Plano - Primera edición</title>
  </programme>
  <programme start="20190221000000 -0300" stop="20190221000000 -0300" channel="Canal 4 Paysandú">
    <title lang="es">Primer Plano - Reiteración</title>
  </programme>
  <programme start="20190221000000 -0300" stop="20190221000000 -0300" channel="Canal 4 Paysandú">
    <title lang="es">Analía tal cual</title>
  </programme>
  <programme start="20190220000000 -0300" stop="20190220000000 -0300" channel="Canal 4 Juan Lacaze">
    <title lang="es">INFORME 4 (Rep)</title>
  </programme>
  <programme start="20190220000000 -0300" stop="20190220000000 -0300" channel="Canal 4 Juan Lacaze">
    <title lang="es">ESPECIALES DE INTERNET</title>
  </programme>
  <programme start="20190220000000 -0300" stop="20190220000000 -0300" channel="Canal 4 Juan Lacaze">
    <title lang="es">HABLEMOS</title>
  </programme>
  <programme start="20190220000000 -0300" stop="20190220000000 -0300" channel="Canal 4 Juan Lacaze">
    <title lang="es">INFORME 4 (REP)</title>
  </programme>
  <programme start="20190220000000 -0300" stop="20190220000000 -0300" channel="Canal 4 Juan Lacaze">
    <title lang="es">HABELMOS (rep)</title>
  </programme>
  <programme start="20190220000000 -0300" stop="20190220000000 -0300" channel="El Canal de la Región - Noreste Canelones">
    <title lang="es">NORESTE NOTICIAS</title>
  </programme>
  <programme start="20190220000000 -0300" stop="20190220000000 -0300" channel="El Canal de la Región - Noreste Canelones">
    <title lang="es">NORESTE NOTICIAS</title>
  </programme>
  <programme start="20190220000000 -0300" stop="20190220000000 -0300" channel="El Canal de la Región - Noreste Canelones">
    <title lang="es">NORESTE NOTICIAS</title>
  </programme>
  <programme start="20190220000000 -0300" stop="20190220000000 -0300" channel="El Canal de la Región - Noreste Canelones">
    <title lang="es">NORESTE NOTICIAS</title>
  </programme>
  <programme start="20190220000000 -0300" stop="20190220000000 -0300" channel="El Canal de la Región - Noreste Canelones">
    <title lang="es">LO MEJOR DE LA SEMANA</title>
  </programme>
  <programme start="20190220070000 -0300" stop="20190220070000 -0300" channel="Canal 8 Durazno">
    <title lang="es">Diálogo Rural</title>
  </programme>
  <programme start="20190220070000 -0300" stop="20190220070000 -0300" channel="Canal 8 Durazno">
    <title lang="es">Diálogo Rural</title>
  </programme>
  <programme start="20190220070000 -0300" stop="20190220070000 -0300" channel="Canal 8 Durazno">
    <title lang="es">Diálogo Rural</title>
  </programme>
  <programme start="20190220090000 -0300" stop="20190220090000 -0300" channel="Canal 8 Durazno">
    <title lang="es">Lo Mejor de La Mañana</title>
  </programme>
  <programme start="20190220090000 -0300" stop="20190220090000 -0300" channel="Canal 8 Durazno">
    <title lang="es">Lo Mejor de La Mañana</title>
  </programme>
  <programme start="20190220000000 -0300" stop="20190220000000 -0300" channel="Canal 4 Salto">
    <title lang="es">Ando Buscando un Socio</title>
  </programme>
  <programme start="20190220000000 -0300" stop="20190220000000 -0300" channel="Canal 4 Salto">
    <title lang="es">La noche del 4</title>
  </programme>
  <programme start="20190220000000 -0300" stop="20190220000000 -0300" channel="Canal 4 Salto">
    <title lang="es">Cine Club</title>
  </programme>
  <programme start="20190220000000 -0300" stop="20190220000000 -0300" channel="Canal 4 Salto">
    <title lang="es">Primer Plano</title>
  </programme>
  <programme start="20190220000000 -0300" stop="20190220000000 -0300" channel="Canal 4 Salto">
    <title lang="es">Cine Club</title>
  </programme>
  <programme start="20190220000000 -0300" stop="20190220000000 -0300" channel="Canal 2 San Carlos">
    <title lang="es">JUNTA DPTAL</title>
  </programme>
  <programme start="20190220000000 -0300" stop="20190220000000 -0300" channel="Canal 2 San Carlos">
    <title lang="es">IGLESIA</title>
  </programme>
  <programme start="20190220000000 -0300" stop="20190220000000 -0300" channel="Canal 2 San Carlos">
    <title lang="es">Iglesia</title>
  </programme>
  <programme start="20190220000000 -0300" stop="20190220000000 -0300" channel="Canal 2 San Carlos">
    <title lang="es">IGLESIA</title>
  </programme>
  <programme start="20190220000000 -0300" stop="20190220000000 -0300" channel="Canal 2 San Carlos">
    <title lang="es">JUNTA DEPTAL</title>
  </programme>
</tv>